radari/__init__.py
radari/main.py
radari-0.0.1.dist-info/LICENSE
radari-0.0.1.dist-info/METADATA
radari-0.0.1.dist-info/WHEEL
radari-0.0.1.dist-info/top_level.txt
radari-0.0.1.dist-info/RECORD
